opentps/gui/__init__.py
opentps/gui/examples/extension/extension/__init__.py
opentps/gui/examples/extension/extension/gui/__init__.py
opentps/gui/examples/extension/extension/gui/extensionPanel.py
opentps/gui/examples/extension/extension/main.py
opentps/gui/examples/extension/extension/utils.py
opentps/gui/main.py
opentps/gui/mainWindow.py
opentps/gui/panels/__init__.py
opentps/gui/panels/breathingSignalPanel.py
opentps/gui/panels/doseComparisonPanel.py
opentps/gui/panels/doseComputationPanel.py
opentps/gui/panels/drrPanel.py
opentps/gui/panels/mainToolbar.py
opentps/gui/panels/patientDataPanel/__init__.py
opentps/gui/panels/patientDataPanel/patientDataMenu.py
opentps/gui/panels/patientDataPanel/patientDataPanel.py
opentps/gui/panels/patientDataPanel/patientDataSelection.py
opentps/gui/panels/patientDataWidgets.py
opentps/gui/panels/planDesignPanel/__init__.py
opentps/gui/panels/planDesignPanel/beamDialog.py
opentps/gui/panels/planDesignPanel/planDesignPanel.py
opentps/gui/panels/planDesignPanel/robustnessSettings.py
opentps/gui/panels/planEvaluationPanel.py
opentps/gui/panels/planOptimizationPanel/__init__.py
opentps/gui/panels/planOptimizationPanel/objectivesWindow.py
opentps/gui/panels/planOptimizationPanel/optimizationSettings.py
opentps/gui/panels/planOptimizationPanel/planOptiPanel.py
opentps/gui/panels/registrationPanel.py
opentps/gui/panels/roiPanel.py
opentps/gui/panels/scriptingPanel/__init__.py
opentps/gui/panels/scriptingPanel/pythonHighlighter.py
opentps/gui/panels/scriptingPanel/scriptingPanel.py
opentps/gui/panels/scriptingPanel/scriptingWindow.py
opentps/gui/programSettingEditor.py
opentps/gui/res/icons/arrow-135.png
opentps/gui/res/icons/chain-unchain.png
opentps/gui/res/icons/chain.png
opentps/gui/res/icons/chart.png
opentps/gui/res/icons/color-adjustment.png
opentps/gui/res/icons/color.png
opentps/gui/res/icons/colormap_histogram.png
opentps/gui/res/icons/colormap_jet.png
opentps/gui/res/icons/contrast.png
opentps/gui/res/icons/crop.png
opentps_gui-2.0.0.dist-info/entry_points.txt
opentps_gui-2.0.0.dist-info/LICENSE
opentps_gui-2.0.0.dist-info/METADATA
opentps_gui-2.0.0.dist-info/WHEEL
opentps_gui-2.0.0.dist-info/RECORD
