Metadata-Version: 2.3
Name: opentps-gui
Version: 2.0.0
Summary: Open source TPS for advanced proton therapy
Home-page: http://opentps.org/
License: GPLv3
Author: Sylvain Deffet
Author-email: sylvaindeffet@gmail.com
Requires-Python: >=3.11,<3.12
Classifier: License :: Other/Proprietary License
Classifier: Programming Language :: Python :: 3
Classifier: Programming Language :: Python :: 3.11
Requires-Dist: Pillow (>=9.4.0,<10.0.0)
Requires-Dist: PyQt5 (==5.15.10)
Requires-Dist: PyQt5-Qt5 (==5.15.2)
Requires-Dist: SimpleITK (>=2.2.1,<3.0.0)
Requires-Dist: cachecontrol
Requires-Dist: numpy (>=1.26.4,<2.0.0)
Requires-Dist: pandas (>=2.2.3,<3.0.0)
Requires-Dist: pydicom (>=3.0.1,<4.0.0)
Requires-Dist: pymedphys (>=0.40.0,<0.41.0)
Requires-Dist: pyqtgraph (>=0.13.1,<0.14.0)
Requires-Dist: scikit-image
Requires-Dist: setuptools (>=67.8.0,<68.0.0)
Requires-Dist: sparse-dot-mkl (>=0.9.6,<0.10.0)
Requires-Dist: vtk (==9.2.6)
